odoo/addons/hr_expense_cancel/README.rst
odoo/addons/hr_expense_cancel/__init__.py
odoo/addons/hr_expense_cancel/__manifest__.py
odoo/addons/hr_expense_cancel/i18n/es.po
odoo/addons/hr_expense_cancel/i18n/hr_expense_cancel.pot
odoo/addons/hr_expense_cancel/i18n/it.po
odoo/addons/hr_expense_cancel/models/__init__.py
odoo/addons/hr_expense_cancel/models/account_payment.py
odoo/addons/hr_expense_cancel/models/hr_expense.py
odoo/addons/hr_expense_cancel/readme/CONTRIBUTORS.md
odoo/addons/hr_expense_cancel/readme/DESCRIPTION.md
odoo/addons/hr_expense_cancel/readme/INSTALL.md
odoo/addons/hr_expense_cancel/readme/USAGE.md
odoo/addons/hr_expense_cancel/static/description/icon.png
odoo/addons/hr_expense_cancel/static/description/index.html
odoo/addons/hr_expense_cancel/tests/__init__.py
odoo/addons/hr_expense_cancel/tests/test_hr_expense_cancel.py
odoo/addons/hr_expense_cancel/views/hr_expense_views.xml
odoo_addon_hr_expense_cancel-18.0.1.0.0.5.dist-info/METADATA
odoo_addon_hr_expense_cancel-18.0.1.0.0.5.dist-info/WHEEL
odoo_addon_hr_expense_cancel-18.0.1.0.0.5.dist-info/top_level.txt
odoo_addon_hr_expense_cancel-18.0.1.0.0.5.dist-info/RECORD
